{
  "t_overall_count": {
    "COURT": 207,
    "COURT_STREET": 68,
    "COURT_POSTAL_CODE": 89,
    "COURT_LOCATION": 108,
    "COMPANY": 345,
    "NAME": 419,
    "BIRTH_DATE": 164,
    "NAME_LOCATION": 188,
    "COMPANY_LOCATION": 331,
    "COMPANY_POSTAL_CODE": 133,
    "COMPANY_STREET": 126,
    "NOTARY_STREET": 52,
    "NOTARY_POSTAL_CODE": 52,
    "NOTARY_LOCATION": 160,
    "DATE": 209,
    "HRA/HRB": 170,
    "NAME_STREET": 124,
    "NAME_POSTAL_CODE": 135,
    "NOTARY": 239,
    "DOCUMENT_NUMBER": 185,
    "LOCATION": 8
  },
  "s_overall_count": {
    "COURT": 203,
    "COURT_STREET": 69,
    "COURT_POSTAL_CODE": 81,
    "COURT_LOCATION": 94,
    "COMPANY": 334,
    "NAME": 422,
    "BIRTH_DATE": 167,
    "NAME_LOCATION": 151,
    "COMPANY_LOCATION": 318,
    "COMPANY_POSTAL_CODE": 145,
    "COMPANY_STREET": 136,
    "NOTARY": 235,
    "NOTARY_STREET": 52,
    "NOTARY_POSTAL_CODE": 52,
    "NOTARY_LOCATION": 172,
    "DATE": 201,
    "HRA/HRB": 150,
    "NAME_STREET": 112,
    "NAME_POSTAL_CODE": 118,
    "DOCUMENT_NUMBER": 170,
    "LOCATION": 29
  },
  "jaccard_similarity": 0.7978231292517007
}